pypi_deployment_sample/__init__.py
pypi_deployment_sample/utils.py
pypi_deployment_sample-0.9.2.dist-info/METADATA
pypi_deployment_sample-0.9.2.dist-info/WHEEL
pypi_deployment_sample-0.9.2.dist-info/RECORD
