Metadata-Version: 2.1
Name: pypi-deployment-sample
Version: 0.9.2
Summary: 
Author: Chuang Yu Min
Author-email: chg.yumin@gmail.com
Requires-Python: >=3.12,<4.0
Classifier: Programming Language :: Python :: 3
Classifier: Programming Language :: Python :: 3.12
